gemmology_crystal_geometry-1.0.3.dist-info/RECORD
gemmology_crystal_geometry-1.0.3.dist-info/WHEEL
gemmology_crystal_geometry-1.0.3.dist-info/METADATA
gemmology_crystal_geometry-1.0.3.dist-info/licenses/LICENSE
crystal_geometry/symmetry.py
crystal_geometry/models.py
crystal_geometry/__init__.py
crystal_geometry/modifications.py
crystal_geometry/_accel.py
crystal_geometry/_optim.py
crystal_geometry/geometry.py
crystal_geometry/py.typed
crystal_geometry/_native.cpython-310-darwin.so
crystal_geometry/habits/orthorhombic.py
crystal_geometry/habits/cubic.py
crystal_geometry/habits/hexagonal.py
crystal_geometry/habits/registry.py
crystal_geometry/habits/__init__.py
crystal_geometry/habits/tetragonal.py
crystal_geometry/habits/special.py
crystal_geometry/habits/base.py
crystal_geometry/twins/transforms.py
crystal_geometry/twins/__init__.py
crystal_geometry/twins/laws.py
crystal_geometry/twins/generators.py
crystal_geometry/_native/CMakeLists.txt
crystal_geometry/_native/include/spatial_hash.hpp
crystal_geometry/_native/include/config.hpp
crystal_geometry/_native/include/geometry.hpp
crystal_geometry/_native/src/geometry.cpp
crystal_geometry/_native/src/bindings.cpp
crystal_geometry/_native/src/spatial_hash.cpp
