Metadata-Version: 2.2
Name: gemmology-crystal-geometry
Version: 1.0.3
Summary: 3D crystal geometry engine for crystallographic visualization
Keywords: crystallography,mineralogy,gemmology,geometry,polyhedra,crystal,visualization,3d
Author-Email: Fabian Schuh <fabian@gemmology.dev>
Maintainer-Email: Fabian Schuh <fabian@gemmology.dev>
License: MIT
Classifier: Development Status :: 5 - Production/Stable
Classifier: Intended Audience :: Science/Research
Classifier: Intended Audience :: Education
Classifier: License :: OSI Approved :: MIT License
Classifier: Operating System :: OS Independent
Classifier: Programming Language :: Python :: 3
Classifier: Programming Language :: Python :: 3.10
Classifier: Programming Language :: Python :: 3.11
Classifier: Programming Language :: Python :: 3.12
Classifier: Programming Language :: Python :: 3.13
Classifier: Topic :: Scientific/Engineering
Classifier: Topic :: Scientific/Engineering :: Chemistry
Classifier: Topic :: Scientific/Engineering :: Visualization
Classifier: Typing :: Typed
Project-URL: Homepage, https://crystal-geometry.gemmology.dev
Project-URL: Documentation, https://crystal-geometry.gemmology.dev/docs
Project-URL: Repository, https://github.com/gemmology-dev/crystal-geometry
Project-URL: Issues, https://github.com/gemmology-dev/crystal-geometry/issues
Project-URL: Changelog, https://github.com/gemmology-dev/crystal-geometry/blob/main/CHANGELOG.md
Requires-Python: >=3.10
Requires-Dist: gemmology-cdl-parser>=1.0.0
Requires-Dist: numpy>=1.20.0
Requires-Dist: scipy>=1.7.0
Provides-Extra: dev
Requires-Dist: pytest>=7.0; extra == "dev"
Requires-Dist: pytest-cov>=4.0; extra == "dev"
Requires-Dist: ruff>=0.1.0; extra == "dev"
Requires-Dist: mypy>=1.0; extra == "dev"
Provides-Extra: docs
Requires-Dist: mkdocs>=1.5; extra == "docs"
Requires-Dist: mkdocs-material>=9.0; extra == "docs"
Requires-Dist: mkdocstrings[python]>=0.24; extra == "docs"
Provides-Extra: native
